exponot/__init__.py
exponot/exponot.py
exponot/utils.py
exponot-0.0.5.dist-info/DESCRIPTION.rst
exponot-0.0.5.dist-info/METADATA
exponot-0.0.5.dist-info/RECORD
exponot-0.0.5.dist-info/WHEEL
exponot-0.0.5.dist-info/metadata.json
exponot-0.0.5.dist-info/top_level.txt
