Metadata-Version: 2.0
Name: exponot
Version: 0.0.5
Summary: Exposure Notification reference implementation
Home-page: https://github.com/vietlq/exponot
Author: Viet Le
Author-email: vietlq85@gmail.com
License: UNKNOWN
Keywords: covid-19 exposure notification contact-tracing
Platform: UNKNOWN
Classifier: Development Status :: 3 - Alpha
Classifier: Environment :: Console
Classifier: Intended Audience :: Developers
Classifier: License :: OSI Approved :: Apache Software License
Classifier: Operating System :: OS Independent
Classifier: Programming Language :: Python
Classifier: Programming Language :: Python :: 3
Classifier: Programming Language :: Python :: 3.5
Classifier: Programming Language :: Python :: 3.6
Classifier: Programming Language :: Python :: 3.7
Classifier: Programming Language :: Python :: 3.8
Classifier: Topic :: Software Development :: Libraries :: Python Modules
